[{"hadm_id": 21390688, "admittime": "2135-11-07T02:42:00", "dischtime": "2135-11-07T06:27:00", "deathtime": null, "admission_type": "EU OBSERVATION", "admission_location": "EMERGENCY ROOM", "discharge_location": null, "insurance": "Medicare", "language": "ENGLISH", "marital_status": "WIDOWED", "ethnicity": "BLACK/AFRICAN AMERICAN", "edregtime": "2135-11-06T21:44:00", "edouttime": "2135-11-07T06:27:00", "hospital_expire_flag": 0}, {"hadm_id": 22484749, "admittime": "2137-03-15T22:08:00", "dischtime": "2137-03-18T16:34:00", "deathtime": null, "admission_type": "OBSERVATION ADMIT", "admission_location": "PHYSICIAN REFERRAL", "discharge_location": "REHAB", "insurance": "Medicare", "language": "ENGLISH", "marital_status": "WIDOWED", "ethnicity": "BLACK/AFRICAN AMERICAN", "edregtime": "2137-03-15T15:27:00", "edouttime": "2137-03-16T00:11:00", "hospital_expire_flag": 0}, {"hadm_id": 24294180, "admittime": "2134-09-07T12:00:00", "dischtime": "2134-09-11T13:10:00", "deathtime": null, "admission_type": "SURGICAL SAME DAY ADMISSION", "admission_location": "PHYSICIAN REFERRAL", "discharge_location": "HOME", "insurance": "Medicare", "language": "ENGLISH", "marital_status": "MARRIED", "ethnicity": "BLACK/AFRICAN AMERICAN", "edregtime": null, "edouttime": null, "hospital_expire_flag": 0}]